[
  {
      "集計期間": "2021110116",
      "売上": "780",
      "会計数": "1",
      "会計単価": "780",
      "客数": "1",
      "客単価": "780",
      "商品数": "2",
      "現金支払合計額": "0",
      "現金その他支払合計額": "780",
      "割引額": "0"
  },
  {
      "集計期間": "2021110118",
      "売上": "2940",
      "会計数": "2",
      "会計単価": "1470",
      "客数": "2",
      "客単価": "1470",
      "商品数": "4",
      "現金支払合計額": "1550",
      "現金その他支払合計額": "1390",
      "割引額": "0"
  },
  {
      "集計期間": "2021110214",
      "売上": "1610",
      "会計数": "1",
      "会計単価": "1610",
      "客数": "2",
      "客単価": "805",
      "商品数": "3",
      "現金支払合計額": "1610",
      "現金その他支払合計額": "0",
      "割引額": "0"
  },
  {
      "集計期間": "2021110215",
      "売上": "390",
      "会計数": "1",
      "会計単価": "390",
      "客数": "1",
      "客単価": "390",
      "商品数": "1",
      "現金支払合計額": "390",
      "現金その他支払合計額": "0",
      "割引額": "0"
  },
  {
      "集計期間": "2021110217",
      "売上": "1410",
      "会計数": "2",
      "会計単価": "705",
      "客数": "3",
      "客単価": "470",
      "商品数": "3",
      "現金支払合計額": "600",
      "現金その他支払合計額": "810",
      "割引額": "0"
  },
  {
      "集計期間": "2021110218",
      "売上": "4040",
      "会計数": "2",
      "会計単価": "2020",
      "客数": "2",
      "客単価": "2020",
      "商品数": "5",
      "現金支払合計額": "4040",
      "現金その他支払合計額": "0",
      "割引額": "0"
  },
  {
      "集計期間": "2021110311",
      "売上": "11130",
      "会計数": "4",
      "会計単価": "2782",
      "客数": "6",
      "客単価": "1855",
      "商品数": "17",
      "現金支払合計額": "5390",
      "現金その他支払合計額": "5740",
      "割引額": "0"
  },
  {
      "集計期間": "2021110313",
      "売上": "6420",
      "会計数": "4",
      "会計単価": "1605",
      "客数": "5",
      "客単価": "1284",
      "商品数": "18",
      "現金支払合計額": "6420",
      "現金その他支払合計額": "0",
      "割引額": "-50"
  },
  {
      "集計期間": "2021110315",
      "売上": "840",
      "会計数": "1",
      "会計単価": "840",
      "客数": "1",
      "客単価": "840",
      "商品数": "2",
      "現金支払合計額": "840",
      "現金その他支払合計額": "0",
      "割引額": "0"
  },
  {
      "集計期間": "2021110316",
      "売上": "16440",
      "会計数": "4",
      "会計単価": "4110",
      "客数": "4",
      "客単価": "4110",
      "商品数": "17",
      "現金支払合計額": "1970",
      "現金その他支払合計額": "14470",
      "割引額": "0"
  },
  {
      "集計期間": "2021110318",
      "売上": "1820",
      "会計数": "1",
      "会計単価": "1820",
      "客数": "1",
      "客単価": "1820",
      "商品数": "4",
      "現金支払合計額": "0",
      "現金その他支払合計額": "1820",
      "割引額": "0"
  },
  {
      "集計期間": "2021110515",
      "売上": "1980",
      "会計数": "1",
      "会計単価": "1980",
      "客数": "1",
      "客単価": "1980",
      "商品数": "3",
      "現金支払合計額": "1980",
      "現金その他支払合計額": "0",
      "割引額": "0"
  },
  {
      "集計期間": "2021110519",
      "売上": "1192",
      "会計数": "1",
      "会計単価": "1192",
      "客数": "1",
      "客単価": "1192",
      "商品数": "1",
      "現金支払合計額": "0",
      "現金その他支払合計額": "1192",
      "割引額": "-298"
  },
  {
      "集計期間": "2021110611",
      "売上": "830",
      "会計数": "1",
      "会計単価": "830",
      "客数": "1",
      "客単価": "830",
      "商品数": "1",
      "現金支払合計額": "830",
      "現金その他支払合計額": "0",
      "割引額": "0"
  },
  {
      "集計期間": "2021110612",
      "売上": "14040",
      "会計数": "5",
      "会計単価": "2808",
      "客数": "7",
      "客単価": "2005",
      "商品数": "19",
      "現金支払合計額": "6580",
      "現金その他支払合計額": "7460",
      "割引額": "0"
  },
  {
      "集計期間": "2021110613",
      "売上": "5440",
      "会計数": "2",
      "会計単価": "2720",
      "客数": "4",
      "客単価": "1360",
      "商品数": "8",
      "現金支払合計額": "3940",
      "現金その他支払合計額": "1500",
      "割引額": "0"
  },
  {
      "集計期間": "2021110614",
      "売上": "2580",
      "会計数": "1",
      "会計単価": "2580",
      "客数": "2",
      "客単価": "1290",
      "商品数": "5",
      "現金支払合計額": "0",
      "現金その他支払合計額": "2580",
      "割引額": "0"
  },
  {
      "集計期間": "2021110615",
      "売上": "3520",
      "会計数": "2",
      "会計単価": "1760",
      "客数": "2",
      "客単価": "1760",
      "商品数": "5",
      "現金支払合計額": "3520",
      "現金その他支払合計額": "0",
      "割引額": "0"
  },
  {
      "集計期間": "2021110616",
      "売上": "390",
      "会計数": "1",
      "会計単価": "390",
      "客数": "1",
      "客単価": "390",
      "商品数": "1",
      "現金支払合計額": "390",
      "現金その他支払合計額": "0",
      "割引額": "0"
  },
  {
      "集計期間": "2021110711",
      "売上": "5000",
      "会計数": "2",
      "会計単価": "2500",
      "客数": "2",
      "客単価": "2500",
      "商品数": "9",
      "現金支払合計額": "1620",
      "現金その他支払合計額": "3380",
      "割引額": "0"
  },
  {
      "集計期間": "2021110712",
      "売上": "6930",
      "会計数": "2",
      "会計単価": "3465",
      "客数": "5",
      "客単価": "1386",
      "商品数": "11",
      "現金支払合計額": "2340",
      "現金その他支払合計額": "4590",
      "割引額": "0"
  },
  {
      "集計期間": "2021110713",
      "売上": "1590",
      "会計数": "1",
      "会計単価": "1590",
      "客数": "1",
      "客単価": "1590",
      "商品数": "7",
      "現金支払合計額": "0",
      "現金その他支払合計額": "1590",
      "割引額": "0"
  },
  {
      "集計期間": "2021110715",
      "売上": "1650",
      "会計数": "2",
      "会計単価": "825",
      "客数": "2",
      "客単価": "825",
      "商品数": "2",
      "現金支払合計額": "1650",
      "現金その他支払合計額": "0",
      "割引額": "0"
  },
  {
      "集計期間": "2021110716",
      "売上": "1400",
      "会計数": "1",
      "会計単価": "1400",
      "客数": "1",
      "客単価": "1400",
      "商品数": "2",
      "現金支払合計額": "1400",
      "現金その他支払合計額": "0",
      "割引額": "0"
  },
  {
      "集計期間": "2021110717",
      "売上": "3270",
      "会計数": "1",
      "会計単価": "3270",
      "客数": "2",
      "客単価": "1635",
      "商品数": "5",
      "現金支払合計額": "0",
      "現金その他支払合計額": "3270",
      "割引額": "0"
  },
  {
      "集計期間": "2021110811",
      "売上": "6270",
      "会計数": "4",
      "会計単価": "1567",
      "客数": "4",
      "客単価": "1567",
      "商品数": "9",
      "現金支払合計額": "2400",
      "現金その他支払合計額": "3870",
      "割引額": "0"
  },
  {
      "集計期間": "2021110814",
      "売上": "1170",
      "会計数": "1",
      "会計単価": "1170",
      "客数": "1",
      "客単価": "1170",
      "商品数": "2",
      "現金支払合計額": "1170",
      "現金その他支払合計額": "0",
      "割引額": "0"
  },
  {
      "集計期間": "2021110815",
      "売上": "2290",
      "会計数": "1",
      "会計単価": "2290",
      "客数": "2",
      "客単価": "1145",
      "商品数": "6",
      "現金支払合計額": "0",
      "現金その他支払合計額": "2290",
      "割引額": "0"
  },
  {
      "集計期間": "2021110817",
      "売上": "500",
      "会計数": "1",
      "会計単価": "500",
      "客数": "1",
      "客単価": "500",
      "商品数": "1",
      "現金支払合計額": "0",
      "現金その他支払合計額": "500",
      "割引額": "0"
  },
  {
      "集計期間": "2021110818",
      "売上": "1000",
      "会計数": "1",
      "会計単価": "1000",
      "客数": "1",
      "客単価": "1000",
      "商品数": "1",
      "現金支払合計額": "1000",
      "現金その他支払合計額": "0",
      "割引額": "0"
  },
  {
      "集計期間": "2021110912",
      "売上": "4630",
      "会計数": "1",
      "会計単価": "4630",
      "客数": "3",
      "客単価": "1543",
      "商品数": "6",
      "現金支払合計額": "0",
      "現金その他支払合計額": "4630",
      "割引額": "0"
  },
  {
      "集計期間": "2021110915",
      "売上": "1800",
      "会計数": "1",
      "会計単価": "1800",
      "客数": "1",
      "客単価": "1800",
      "商品数": "3",
      "現金支払合計額": "1800",
      "現金その他支払合計額": "0",
      "割引額": "0"
  },
  {
      "集計期間": "2021110918",
      "売上": "2200",
      "会計数": "2",
      "会計単価": "1100",
      "客数": "2",
      "客単価": "1100",
      "商品数": "2",
      "現金支払合計額": "2200",
      "現金その他支払合計額": "0",
      "割引額": "0"
  },
  {
      "集計期間": "2021111012",
      "売上": "1970",
      "会計数": "2",
      "会計単価": "985",
      "客数": "2",
      "客単価": "985",
      "商品数": "4",
      "現金支払合計額": "1970",
      "現金その他支払合計額": "0",
      "割引額": "0"
  },
  {
      "集計期間": "2021111013",
      "売上": "400",
      "会計数": "1",
      "会計単価": "400",
      "客数": "1",
      "客単価": "400",
      "商品数": "2",
      "現金支払合計額": "400",
      "現金その他支払合計額": "0",
      "割引額": "0"
  },
  {
      "集計期間": "2021111015",
      "売上": "4950",
      "会計数": "2",
      "会計単価": "2475",
      "客数": "2",
      "客単価": "2475",
      "商品数": "33",
      "現金支払合計額": "4000",
      "現金その他支払合計額": "950",
      "割引額": "-160"
  },
  {
      "集計期間": "2021111016",
      "売上": "1450",
      "会計数": "1",
      "会計単価": "1450",
      "客数": "1",
      "客単価": "1450",
      "商品数": "2",
      "現金支払合計額": "1450",
      "現金その他支払合計額": "0",
      "割引額": "-200"
  },
  {
      "集計期間": "2021111017",
      "売上": "10340",
      "会計数": "2",
      "会計単価": "5170",
      "客数": "2",
      "客単価": "5170",
      "商品数": "5",
      "現金支払合計額": "1690",
      "現金その他支払合計額": "8650",
      "割引額": "0"
  },
  {
      "集計期間": "2021111121",
      "売上": "3740",
      "会計数": "1",
      "会計単価": "3740",
      "客数": "1",
      "客単価": "3740",
      "商品数": "5",
      "現金支払合計額": "3740",
      "現金その他支払合計額": "0",
      "割引額": "0"
  },
  {
      "集計期間": "2021111213",
      "売上": "2740",
      "会計数": "1",
      "会計単価": "2740",
      "客数": "2",
      "客単価": "1370",
      "商品数": "4",
      "現金支払合計額": "2740",
      "現金その他支払合計額": "0",
      "割引額": "0"
  },
  {
      "集計期間": "2021111214",
      "売上": "2980",
      "会計数": "1",
      "会計単価": "2980",
      "客数": "1",
      "客単価": "2980",
      "商品数": "1",
      "現金支払合計額": "0",
      "現金その他支払合計額": "2980",
      "割引額": "0"
  },
  {
      "集計期間": "2021111215",
      "売上": "1200",
      "会計数": "1",
      "会計単価": "1200",
      "客数": "1",
      "客単価": "1200",
      "商品数": "1",
      "現金支払合計額": "1200",
      "現金その他支払合計額": "0",
      "割引額": "0"
  },
  {
      "集計期間": "2021111216",
      "売上": "1760",
      "会計数": "1",
      "会計単価": "1760",
      "客数": "1",
      "客単価": "1760",
      "商品数": "2",
      "現金支払合計額": "0",
      "現金その他支払合計額": "1760",
      "割引額": "0"
  },
  {
      "集計期間": "2021111217",
      "売上": "400",
      "会計数": "1",
      "会計単価": "400",
      "客数": "1",
      "客単価": "400",
      "商品数": "1",
      "現金支払合計額": "400",
      "現金その他支払合計額": "0",
      "割引額": "0"
  },
  {
      "集計期間": "2021111218",
      "売上": "5290",
      "会計数": "5",
      "会計単価": "1058",
      "客数": "6",
      "客単価": "881",
      "商品数": "9",
      "現金支払合計額": "2690",
      "現金その他支払合計額": "2600",
      "割引額": "0"
  },
  {
      "集計期間": "2021111312",
      "売上": "21070",
      "会計数": "8",
      "会計単価": "2633",
      "客数": "12",
      "客単価": "1755",
      "商品数": "26",
      "現金支払合計額": "11880",
      "現金その他支払合計額": "9190",
      "割引額": "0"
  },
  {
      "集計期間": "2021111313",
      "売上": "5840",
      "会計数": "3",
      "会計単価": "1946",
      "客数": "4",
      "客単価": "1460",
      "商品数": "11",
      "現金支払合計額": "1390",
      "現金その他支払合計額": "4450",
      "割引額": "0"
  },
  {
      "集計期間": "2021111314",
      "売上": "3210",
      "会計数": "1",
      "会計単価": "3210",
      "客数": "2",
      "客単価": "1605",
      "商品数": "4",
      "現金支払合計額": "3210",
      "現金その他支払合計額": "0",
      "割引額": "0"
  },
  {
      "集計期間": "2021111315",
      "売上": "3530",
      "会計数": "2",
      "会計単価": "1765",
      "客数": "3",
      "客単価": "1176",
      "商品数": "6",
      "現金支払合計額": "0",
      "現金その他支払合計額": "3530",
      "割引額": "0"
  },
  {
      "集計期間": "2021111316",
      "売上": "5400",
      "会計数": "3",
      "会計単価": "1800",
      "客数": "3",
      "客単価": "1800",
      "商品数": "8",
      "現金支払合計額": "2650",
      "現金その他支払合計額": "2750",
      "割引額": "-480"
  },
  {
      "集計期間": "2021111317",
      "売上": "1200",
      "会計数": "1",
      "会計単価": "1200",
      "客数": "1",
      "客単価": "1200",
      "商品数": "1",
      "現金支払合計額": "0",
      "現金その他支払合計額": "1200",
      "割引額": "0"
  },
  {
      "集計期間": "2021111319",
      "売上": "770",
      "会計数": "1",
      "会計単価": "770",
      "客数": "1",
      "客単価": "770",
      "商品数": "2",
      "現金支払合計額": "770",
      "現金その他支払合計額": "0",
      "割引額": "0"
  },
  {
      "集計期間": "2021111412",
      "売上": "5420",
      "会計数": "3",
      "会計単価": "1806",
      "客数": "3",
      "客単価": "1806",
      "商品数": "7",
      "現金支払合計額": "980",
      "現金その他支払合計額": "4440",
      "割引額": "0"
  },
  {
      "集計期間": "2021111413",
      "売上": "7830",
      "会計数": "2",
      "会計単価": "3915",
      "客数": "6",
      "客単価": "1305",
      "商品数": "11",
      "現金支払合計額": "7830",
      "現金その他支払合計額": "0",
      "割引額": "0"
  },
  {
      "集計期間": "2021111414",
      "売上": "5030",
      "会計数": "1",
      "会計単価": "5030",
      "客数": "3",
      "客単価": "1676",
      "商品数": "7",
      "現金支払合計額": "5030",
      "現金その他支払合計額": "0",
      "割引額": "0"
  },
  {
      "集計期間": "2021111415",
      "売上": "3760",
      "会計数": "2",
      "会計単価": "1880",
      "客数": "4",
      "客単価": "940",
      "商品数": "6",
      "現金支払合計額": "3760",
      "現金その他支払合計額": "0",
      "割引額": "0"
  },
  {
      "集計期間": "2021111416",
      "売上": "980",
      "会計数": "3",
      "会計単価": "326",
      "客数": "3",
      "客単価": "326",
      "商品数": "12",
      "現金支払合計額": "0",
      "現金その他支払合計額": "980",
      "割引額": "0"
  },
  {
      "集計期間": "2021111417",
      "売上": "380",
      "会計数": "1",
      "会計単価": "380",
      "客数": "1",
      "客単価": "380",
      "商品数": "1",
      "現金支払合計額": "380",
      "現金その他支払合計額": "0",
      "割引額": "-20"
  },
  {
      "集計期間": "2021111511",
      "売上": "2440",
      "会計数": "1",
      "会計単価": "2440",
      "客数": "2",
      "客単価": "1220",
      "商品数": "4",
      "現金支払合計額": "2440",
      "現金その他支払合計額": "0",
      "割引額": "0"
  },
  {
      "集計期間": "2021111513",
      "売上": "9700",
      "会計数": "1",
      "会計単価": "9700",
      "客数": "1",
      "客単価": "9700",
      "商品数": "3",
      "現金支払合計額": "9700",
      "現金その他支払合計額": "0",
      "割引額": "0"
  },
  {
      "集計期間": "2021111514",
      "売上": "1450",
      "会計数": "1",
      "会計単価": "1450",
      "客数": "1",
      "客単価": "1450",
      "商品数": "2",
      "現金支払合計額": "1450",
      "現金その他支払合計額": "0",
      "割引額": "0"
  },
  {
      "集計期間": "2021111516",
      "売上": "1220",
      "会計数": "2",
      "会計単価": "610",
      "客数": "2",
      "客単価": "610",
      "商品数": "2",
      "現金支払合計額": "1220",
      "現金その他支払合計額": "0",
      "割引額": "0"
  },
  {
      "集計期間": "2021111517",
      "売上": "800",
      "会計数": "1",
      "会計単価": "800",
      "客数": "1",
      "客単価": "800",
      "商品数": "2",
      "現金支払合計額": "800",
      "現金その他支払合計額": "0",
      "割引額": "0"
  },
  {
      "集計期間": "2021111618",
      "売上": "2170",
      "会計数": "1",
      "会計単価": "2170",
      "客数": "1",
      "客単価": "2170",
      "商品数": "3",
      "現金支払合計額": "2170",
      "現金その他支払合計額": "0",
      "割引額": "0"
  },
  {
      "集計期間": "2021111712",
      "売上": "6000",
      "会計数": "2",
      "会計単価": "3000",
      "客数": "2",
      "客単価": "3000",
      "商品数": "5",
      "現金支払合計額": "6000",
      "現金その他支払合計額": "0",
      "割引額": "0"
  },
  {
      "集計期間": "2021111714",
      "売上": "2010",
      "会計数": "2",
      "会計単価": "1005",
      "客数": "2",
      "客単価": "1005",
      "商品数": "5",
      "現金支払合計額": "2010",
      "現金その他支払合計額": "0",
      "割引額": "0"
  },
  {
      "集計期間": "2021111717",
      "売上": "4530",
      "会計数": "2",
      "会計単価": "2265",
      "客数": "3",
      "客単価": "1510",
      "商品数": "7",
      "現金支払合計額": "4530",
      "現金その他支払合計額": "0",
      "割引額": "0"
  },
  {
      "集計期間": "2021111718",
      "売上": "980",
      "会計数": "1",
      "会計単価": "980",
      "客数": "1",
      "客単価": "980",
      "商品数": "1",
      "現金支払合計額": "980",
      "現金その他支払合計額": "0",
      "割引額": "0"
  },
  {
      "集計期間": "2021111912",
      "売上": "2230",
      "会計数": "1",
      "会計単価": "2230",
      "客数": "2",
      "客単価": "1115",
      "商品数": "3",
      "現金支払合計額": "2230",
      "現金その他支払合計額": "0",
      "割引額": "0"
  },
  {
      "集計期間": "2021111913",
      "売上": "4130",
      "会計数": "3",
      "会計単価": "1376",
      "客数": "4",
      "客単価": "1032",
      "商品数": "8",
      "現金支払合計額": "4130",
      "現金その他支払合計額": "0",
      "割引額": "0"
  },
  {
      "集計期間": "2021111915",
      "売上": "2990",
      "会計数": "1",
      "会計単価": "2990",
      "客数": "1",
      "客単価": "2990",
      "商品数": "2",
      "現金支払合計額": "0",
      "現金その他支払合計額": "2990",
      "割引額": "0"
  },
  {
      "集計期間": "2021111917",
      "売上": "380",
      "会計数": "1",
      "会計単価": "380",
      "客数": "1",
      "客単価": "380",
      "商品数": "1",
      "現金支払合計額": "380",
      "現金その他支払合計額": "0",
      "割引額": "-20"
  },
  {
      "集計期間": "2021111918",
      "売上": "8360",
      "会計数": "3",
      "会計単価": "2786",
      "客数": "4",
      "客単価": "2090",
      "商品数": "11",
      "現金支払合計額": "3630",
      "現金その他支払合計額": "4730",
      "割引額": "-2000"
  },
  {
      "集計期間": "2021112011",
      "売上": "5940",
      "会計数": "2",
      "会計単価": "2970",
      "客数": "4",
      "客単価": "1485",
      "商品数": "5",
      "現金支払合計額": "5940",
      "現金その他支払合計額": "0",
      "割引額": "0"
  },
  {
      "集計期間": "2021112012",
      "売上": "10000",
      "会計数": "3",
      "会計単価": "3333",
      "客数": "4",
      "客単価": "2500",
      "商品数": "12",
      "現金支払合計額": "10000",
      "現金その他支払合計額": "0",
      "割引額": "0"
  },
  {
      "集計期間": "2021112013",
      "売上": "3180",
      "会計数": "1",
      "会計単価": "3180",
      "客数": "2",
      "客単価": "1590",
      "商品数": "4",
      "現金支払合計額": "0",
      "現金その他支払合計額": "3180",
      "割引額": "0"
  },
  {
      "集計期間": "2021112014",
      "売上": "7240",
      "会計数": "3",
      "会計単価": "2413",
      "客数": "5",
      "客単価": "1448",
      "商品数": "11",
      "現金支払合計額": "7240",
      "現金その他支払合計額": "0",
      "割引額": "0"
  },
  {
      "集計期間": "2021112015",
      "売上": "4070",
      "会計数": "3",
      "会計単価": "1356",
      "客数": "4",
      "客単価": "1017",
      "商品数": "5",
      "現金支払合計額": "4070",
      "現金その他支払合計額": "0",
      "割引額": "0"
  },
  {
      "集計期間": "2021112016",
      "売上": "500",
      "会計数": "1",
      "会計単価": "500",
      "客数": "1",
      "客単価": "500",
      "商品数": "1",
      "現金支払合計額": "500",
      "現金その他支払合計額": "0",
      "割引額": "0"
  },
  {
      "集計期間": "2021112018",
      "売上": "1150",
      "会計数": "1",
      "会計単価": "1150",
      "客数": "1",
      "客単価": "1150",
      "商品数": "2",
      "現金支払合計額": "0",
      "現金その他支払合計額": "1150",
      "割引額": "0"
  },
  {
      "集計期間": "2021112111",
      "売上": "6990",
      "会計数": "2",
      "会計単価": "3495",
      "客数": "4",
      "客単価": "1747",
      "商品数": "10",
      "現金支払合計額": "0",
      "現金その他支払合計額": "6990",
      "割引額": "0"
  },
  {
      "集計期間": "2021112113",
      "売上": "5770",
      "会計数": "3",
      "会計単価": "1923",
      "客数": "5",
      "客単価": "1154",
      "商品数": "6",
      "現金支払合計額": "3080",
      "現金その他支払合計額": "2690",
      "割引額": "0"
  },
  {
      "集計期間": "2021112114",
      "売上": "3530",
      "会計数": "1",
      "会計単価": "3530",
      "客数": "2",
      "客単価": "1765",
      "商品数": "6",
      "現金支払合計額": "0",
      "現金その他支払合計額": "3530",
      "割引額": "0"
  },
  {
      "集計期間": "2021112115",
      "売上": "9560",
      "会計数": "2",
      "会計単価": "4780",
      "客数": "4",
      "客単価": "2390",
      "商品数": "12",
      "現金支払合計額": "6380",
      "現金その他支払合計額": "3180",
      "割引額": "0"
  },
  {
      "集計期間": "2021112117",
      "売上": "5220",
      "会計数": "3",
      "会計単価": "1740",
      "客数": "3",
      "客単価": "1740",
      "商品数": "8",
      "現金支払合計額": "3990",
      "現金その他支払合計額": "1230",
      "割引額": "0"
  },
  {
      "集計期間": "2021112212",
      "売上": "200",
      "会計数": "1",
      "会計単価": "200",
      "客数": "1",
      "客単価": "200",
      "商品数": "1",
      "現金支払合計額": "200",
      "現金その他支払合計額": "0",
      "割引額": "0"
  },
  {
      "集計期間": "2021112215",
      "売上": "5770",
      "会計数": "2",
      "会計単価": "2885",
      "客数": "2",
      "客単価": "2885",
      "商品数": "9",
      "現金支払合計額": "0",
      "現金その他支払合計額": "5770",
      "割引額": "0"
  },
  {
      "集計期間": "2021112217",
      "売上": "3180",
      "会計数": "2",
      "会計単価": "1590",
      "客数": "2",
      "客単価": "1590",
      "商品数": "5",
      "現金支払合計額": "3180",
      "現金その他支払合計額": "0",
      "割引額": "0"
  },
  {
      "集計期間": "2021112219",
      "売上": "400",
      "会計数": "1",
      "会計単価": "400",
      "客数": "1",
      "客単価": "400",
      "商品数": "1",
      "現金支払合計額": "400",
      "現金その他支払合計額": "0",
      "割引額": "0"
  },
  {
      "集計期間": "2021112311",
      "売上": "4180",
      "会計数": "3",
      "会計単価": "1393",
      "客数": "6",
      "客単価": "696",
      "商品数": "10",
      "現金支払合計額": "2590",
      "現金その他支払合計額": "1590",
      "割引額": "0"
  },
  {
      "集計期間": "2021112313",
      "売上": "6950",
      "会計数": "3",
      "会計単価": "2316",
      "客数": "5",
      "客単価": "1390",
      "商品数": "11",
      "現金支払合計額": "6950",
      "現金その他支払合計額": "0",
      "割引額": "0"
  },
  {
      "集計期間": "2021112314",
      "売上": "3820",
      "会計数": "3",
      "会計単価": "1273",
      "客数": "3",
      "客単価": "1273",
      "商品数": "8",
      "現金支払合計額": "3010",
      "現金その他支払合計額": "810",
      "割引額": "0"
  },
  {
      "集計期間": "2021112319",
      "売上": "1000",
      "会計数": "1",
      "会計単価": "1000",
      "客数": "1",
      "客単価": "1000",
      "商品数": "2",
      "現金支払合計額": "1000",
      "現金その他支払合計額": "0",
      "割引額": "-600"
  },
  {
      "集計期間": "2021112413",
      "売上": "1830",
      "会計数": "2",
      "会計単価": "915",
      "客数": "2",
      "客単価": "915",
      "商品数": "2",
      "現金支払合計額": "1830",
      "現金その他支払合計額": "0",
      "割引額": "0"
  },
  {
      "集計期間": "2021112414",
      "売上": "5590",
      "会計数": "2",
      "会計単価": "2795",
      "客数": "2",
      "客単価": "2795",
      "商品数": "32",
      "現金支払合計額": "5590",
      "現金その他支払合計額": "0",
      "割引額": "0"
  },
  {
      "集計期間": "2021112417",
      "売上": "3026",
      "会計数": "2",
      "会計単価": "1513",
      "客数": "2",
      "客単価": "1513",
      "商品数": "3",
      "現金支払合計額": "2376",
      "現金その他支払合計額": "650",
      "割引額": "-264"
  },
  {
      "集計期間": "2021112418",
      "売上": "390",
      "会計数": "1",
      "会計単価": "390",
      "客数": "1",
      "客単価": "390",
      "商品数": "1",
      "現金支払合計額": "390",
      "現金その他支払合計額": "0",
      "割引額": "0"
  },
  {
      "集計期間": "2021112612",
      "売上": "1550",
      "会計数": "1",
      "会計単価": "1550",
      "客数": "1",
      "客単価": "1550",
      "商品数": "2",
      "現金支払合計額": "1550",
      "現金その他支払合計額": "0",
      "割引額": "0"
  },
  {
      "集計期間": "2021112615",
      "売上": "3180",
      "会計数": "1",
      "会計単価": "3180",
      "客数": "2",
      "客単価": "1590",
      "商品数": "5",
      "現金支払合計額": "3180",
      "現金その他支払合計額": "0",
      "割引額": "0"
  },
  {
      "集計期間": "2021112616",
      "売上": "3390",
      "会計数": "2",
      "会計単価": "1695",
      "客数": "2",
      "客単価": "1695",
      "商品数": "3",
      "現金支払合計額": "0",
      "現金その他支払合計額": "3390",
      "割引額": "0"
  },
  {
      "集計期間": "2021112617",
      "売上": "3180",
      "会計数": "1",
      "会計単価": "3180",
      "客数": "1",
      "客単価": "3180",
      "商品数": "4",
      "現金支払合計額": "0",
      "現金その他支払合計額": "3180",
      "割引額": "0"
  },
  {
      "集計期間": "2021112712",
      "売上": "650",
      "会計数": "1",
      "会計単価": "650",
      "客数": "1",
      "客単価": "650",
      "商品数": "1",
      "現金支払合計額": "650",
      "現金その他支払合計額": "0",
      "割引額": "0"
  },
  {
      "集計期間": "2021112713",
      "売上": "5180",
      "会計数": "3",
      "会計単価": "1726",
      "客数": "4",
      "客単価": "1295",
      "商品数": "6",
      "現金支払合計額": "4200",
      "現金その他支払合計額": "980",
      "割引額": "0"
  },
  {
      "集計期間": "2021112714",
      "売上": "2200",
      "会計数": "1",
      "会計単価": "2200",
      "客数": "2",
      "客単価": "1100",
      "商品数": "2",
      "現金支払合計額": "2200",
      "現金その他支払合計額": "0",
      "割引額": "0"
  },
  {
      "集計期間": "2021112717",
      "売上": "5541",
      "会計数": "3",
      "会計単価": "1847",
      "客数": "4",
      "客単価": "1385",
      "商品数": "10",
      "現金支払合計額": "1841",
      "現金その他支払合計額": "3700",
      "割引額": "-99"
  },
  {
      "集計期間": "2021112718",
      "売上": "790",
      "会計数": "1",
      "会計単価": "790",
      "客数": "1",
      "客単価": "790",
      "商品数": "2",
      "現金支払合計額": "0",
      "現金その他支払合計額": "790",
      "割引額": "0"
  },
  {
      "集計期間": "2021112719",
      "売上": "5210",
      "会計数": "1",
      "会計単価": "5210",
      "客数": "1",
      "客単価": "5210",
      "商品数": "3",
      "現金支払合計額": "0",
      "現金その他支払合計額": "5210",
      "割引額": "-1690"
  },
  {
      "集計期間": "2021112811",
      "売上": "5040",
      "会計数": "2",
      "会計単価": "2520",
      "客数": "3",
      "客単価": "1680",
      "商品数": "7",
      "現金支払合計額": "5040",
      "現金その他支払合計額": "0",
      "割引額": "-270"
  },
  {
      "集計期間": "2021112812",
      "売上": "9690",
      "会計数": "4",
      "会計単価": "2422",
      "客数": "5",
      "客単価": "1938",
      "商品数": "10",
      "現金支払合計額": "6850",
      "現金その他支払合計額": "2840",
      "割引額": "-1750"
  },
  {
      "集計期間": "2021112813",
      "売上": "13160",
      "会計数": "4",
      "会計単価": "3290",
      "客数": "8",
      "客単価": "1645",
      "商品数": "22",
      "現金支払合計額": "13160",
      "現金その他支払合計額": "0",
      "割引額": "0"
  },
  {
      "集計期間": "2021112814",
      "売上": "5730",
      "会計数": "2",
      "会計単価": "2865",
      "客数": "4",
      "客単価": "1432",
      "商品数": "7",
      "現金支払合計額": "5730",
      "現金その他支払合計額": "0",
      "割引額": "0"
  },
  {
      "集計期間": "2021112815",
      "売上": "5730",
      "会計数": "1",
      "会計単価": "5730",
      "客数": "1",
      "客単価": "5730",
      "商品数": "3",
      "現金支払合計額": "0",
      "現金その他支払合計額": "5730",
      "割引額": "-1750"
  },
  {
      "集計期間": "2021112816",
      "売上": "2370",
      "会計数": "3",
      "会計単価": "790",
      "客数": "3",
      "客単価": "790",
      "商品数": "5",
      "現金支払合計額": "2370",
      "現金その他支払合計額": "0",
      "割引額": "0"
  },
  {
      "集計期間": "2021112817",
      "売上": "7560",
      "会計数": "2",
      "会計単価": "3780",
      "客数": "5",
      "客単価": "1512",
      "商品数": "12",
      "現金支払合計額": "7560",
      "現金その他支払合計額": "0",
      "割引額": "0"
  },
  {
      "集計期間": "2021112818",
      "売上": "0",
      "会計数": "2",
      "会計単価": "0",
      "客数": "2",
      "客単価": "0",
      "商品数": "14",
      "現金支払合計額": "0",
      "現金その他支払合計額": "0",
      "割引額": "0"
  },
  {
      "集計期間": "2021112819",
      "売上": "3570",
      "会計数": "2",
      "会計単価": "1785",
      "客数": "2",
      "客単価": "1785",
      "商品数": "2",
      "現金支払合計額": "0",
      "現金その他支払合計額": "3570",
      "割引額": "-1350"
  },
  {
      "集計期間": "2021112911",
      "売上": "33010",
      "会計数": "4",
      "会計単価": "8252",
      "客数": "4",
      "客単価": "8252",
      "商品数": "8",
      "現金支払合計額": "2440",
      "現金その他支払合計額": "30570",
      "割引額": "0"
  },
  {
      "集計期間": "2021112918",
      "売上": "3100",
      "会計数": "1",
      "会計単価": "3100",
      "客数": "3",
      "客単価": "1033",
      "商品数": "3",
      "現金支払合計額": "3100",
      "現金その他支払合計額": "0",
      "割引額": "0"
  },
  {
      "集計期間": "2021113011",
      "売上": "2290",
      "会計数": "1",
      "会計単価": "2290",
      "客数": "1",
      "客単価": "2290",
      "商品数": "3",
      "現金支払合計額": "2290",
      "現金その他支払合計額": "0",
      "割引額": "0"
  },
  {
      "集計期間": "2021113012",
      "売上": "5868",
      "会計数": "2",
      "会計単価": "2934",
      "客数": "2",
      "客単価": "2934",
      "商品数": "8",
      "現金支払合計額": "1790",
      "現金その他支払合計額": "4078",
      "割引額": "-722"
  },
  {
      "集計期間": "2021113015",
      "売上": "7090",
      "会計数": "2",
      "会計単価": "3545",
      "客数": "2",
      "客単価": "3545",
      "商品数": "8",
      "現金支払合計額": "1240",
      "現金その他支払合計額": "5850",
      "割引額": "0"
  },
  {
      "集計期間": "2021113018",
      "売上": "2400",
      "会計数": "1",
      "会計単価": "2400",
      "客数": "1",
      "客単価": "2400",
      "商品数": "2",
      "現金支払合計額": "2400",
      "現金その他支払合計額": "0",
      "割引額": "0"
  }
]